{"cameraMode":{"drawMode":0,"name":"Shaded","section":"Shading Mode"},"sceneLighting":true,"audioPlay":false,"sceneViewState":{"m_AlwaysRefresh":false,"showFog":true,"showSkybox":true,"showFlares":true,"showImageEffects":true,"showParticleSystems":true,"showVisualEffectGraphs":true,"m_FxEnabled":true},"in2DMode":false,"pivot":{"x":5.816699981689453,"y":1.0299999713897706,"z":-1.1451836824417115},"rotation":{"x":-0.0014678146690130234,"y":-0.998729407787323,"z":0.0362749844789505,"w":-0.0363120436668396},"size":1.017196536064148,"orthographic":false}